gerrymetrics/__init__.py
gerrymetrics/metrics.py
gerrymetrics/plots.py
gerrymetrics/utils.py
gerrymetrics-0.1.3.dist-info/METADATA
gerrymetrics-0.1.3.dist-info/RECORD
gerrymetrics-0.1.3.dist-info/WHEEL
gerrymetrics-0.1.3.dist-info/top_level.txt
