Metadata-Version: 2.1
Name: gerrymetrics
Version: 0.1.3
Summary: Lots of metrics for quantifying gerrymandering
Home-page: https://github.com/PrincetonUniversity/gerrymandertests
Author: Princeton Gerrymandering Project
Author-email: wtadler@princeton.edu
License: GNU General Public License v3.0
Platform: UNKNOWN
Requires-Dist: pandas
Requires-Dist: numpy
Requires-Dist: scipy
Requires-Dist: matplotlib
Requires-Dist: tqdm
